pageindex/__init__.py
pageindex/client.py
pageindex/utils.py
pageindex-0.2.5.dist-info/METADATA
pageindex-0.2.5.dist-info/WHEEL
pageindex-0.2.5.dist-info/RECORD
