Metadata-Version: 2.3
Name: pageindex
Version: 0.2.5
Summary: Python SDK for PageIndex
Author: Ray
Author-email: ray@vectify.ai
Requires-Python: >=3.7
Classifier: Programming Language :: Python :: 3
Classifier: Programming Language :: Python :: 3.7
Classifier: Programming Language :: Python :: 3.8
Classifier: Programming Language :: Python :: 3.9
Classifier: Programming Language :: Python :: 3.10
Classifier: Programming Language :: Python :: 3.11
Classifier: Programming Language :: Python :: 3.12
Classifier: Programming Language :: Python :: 3.13
Requires-Dist: openai (>=1.70.0)
Requires-Dist: requests (>=2.25.0,<3.0.0)
